bazoo/__init__.py
bazoo/core.py
bazoo-0.1.0.dist-info/LICENSE
bazoo-0.1.0.dist-info/METADATA
bazoo-0.1.0.dist-info/WHEEL
bazoo-0.1.0.dist-info/top_level.txt
bazoo-0.1.0.dist-info/RECORD
