Metadata-Version: 2.2
Name: bazoo
Version: 0.1.0
Summary: Unofficial Python library for BazooStore API - Access bots from Bale messenger's bot store
Home-page: 
Author: Hamidreza
Author-email: h4midrezam@gmail.com
Classifier: Programming Language :: Python :: 3
Classifier: License :: OSI Approved :: MIT License
Classifier: Operating System :: OS Independent
Requires-Python: >=3.6
License-File: LICENSE
Requires-Dist: requests
Dynamic: author
Dynamic: author-email
Dynamic: classifier
Dynamic: description
Dynamic: description-content-type
Dynamic: requires-dist
Dynamic: requires-python
Dynamic: summary
